{
    "locked": false, 
    "name": "FXPAL_Outside_Walkaround_1", 
    "recs": [
        {
            "pos": [
                37.40580284, 
                -122.15108964, 
                12.0
            ], 
            "time": 1468478751.0
        }, 
        {
            "pos": [
                37.40581179, 
                -122.15107496, 
                12.0
            ], 
            "time": 1468478752.0
        }, 
        {
            "pos": [
                37.40582064, 
                -122.15106968, 
                12.0
            ], 
            "time": 1468478753.0
        }, 
        {
            "pos": [
                37.40582489, 
                -122.1510604, 
                12.0
            ], 
            "time": 1468478754.0
        }, 
        {
            "pos": [
                37.40582985, 
                -122.15106462, 
                12.0
            ], 
            "time": 1468478755.0
        }, 
        {
            "pos": [
                37.40583725, 
                -122.15106421, 
                11.0
            ], 
            "time": 1468478756.0
        }, 
        {
            "pos": [
                37.40583442, 
                -122.15106829, 
                11.0
            ], 
            "time": 1468478757.0
        }, 
        {
            "pos": [
                37.40583017, 
                -122.15107049, 
                11.0
            ], 
            "time": 1468478758.0
        }, 
        {
            "pos": [
                37.40583137, 
                -122.15107228, 
                11.0
            ], 
            "time": 1468478759.0
        }, 
        {
            "pos": [
                37.40583585, 
                -122.15107115, 
                13.0
            ], 
            "time": 1468478760.0
        }, 
        {
            "pos": [
                37.40583422, 
                -122.15107518, 
                13.0
            ], 
            "time": 1468478761.0
        }, 
        {
            "pos": [
                37.40583492, 
                -122.15107469, 
                12.0
            ], 
            "time": 1468478762.0
        }, 
        {
            "pos": [
                37.4058353, 
                -122.1510747, 
                12.0
            ], 
            "time": 1468478763.0
        }, 
        {
            "pos": [
                37.40583569, 
                -122.15107472, 
                12.0
            ], 
            "time": 1468478764.0
        }, 
        {
            "pos": [
                37.4058359, 
                -122.15107469, 
                12.0
            ], 
            "time": 1468478765.0
        }, 
        {
            "pos": [
                37.40583596, 
                -122.15107468, 
                12.0
            ], 
            "time": 1468478766.0
        }, 
        {
            "pos": [
                37.40583598, 
                -122.15107467, 
                12.0
            ], 
            "time": 1468478767.0
        }, 
        {
            "pos": [
                37.40583612, 
                -122.15107471, 
                12.0
            ], 
            "time": 1468478768.0
        }, 
        {
            "pos": [
                37.40583623, 
                -122.15107475, 
                12.0
            ], 
            "time": 1468478769.0
        }, 
        {
            "pos": [
                37.40583645, 
                -122.15107475, 
                14.0
            ], 
            "time": 1468478770.0
        }, 
        {
            "pos": [
                37.40583653, 
                -122.15107478, 
                13.0
            ], 
            "time": 1468478771.0
        }, 
        {
            "pos": [
                37.40583658, 
                -122.15107481, 
                13.0
            ], 
            "time": 1468478772.0
        }, 
        {
            "pos": [
                37.40583646, 
                -122.15107493, 
                12.0
            ], 
            "time": 1468478773.0
        }, 
        {
            "pos": [
                37.40583642, 
                -122.151075, 
                12.0
            ], 
            "time": 1468478774.0
        }, 
        {
            "pos": [
                37.40583644, 
                -122.15107505, 
                12.0
            ], 
            "time": 1468478775.0
        }, 
        {
            "pos": [
                37.40583639, 
                -122.15107516, 
                12.0
            ], 
            "time": 1468478776.0
        }, 
        {
            "pos": [
                37.40583638, 
                -122.15107519, 
                12.0
            ], 
            "time": 1468478777.0
        }, 
        {
            "pos": [
                37.40583637, 
                -122.15107522, 
                12.0
            ], 
            "time": 1468478778.0
        }, 
        {
            "pos": [
                37.40583627, 
                -122.15107535, 
                12.0
            ], 
            "time": 1468478779.0
        }, 
        {
            "pos": [
                37.40583646, 
                -122.15107536, 
                12.0
            ], 
            "time": 1468478780.0
        }, 
        {
            "pos": [
                37.40583656, 
                -122.15107539, 
                12.0
            ], 
            "time": 1468478781.0
        }, 
        {
            "pos": [
                37.40583662, 
                -122.15107549, 
                12.0
            ], 
            "time": 1468478782.0
        }, 
        {
            "pos": [
                37.40583665, 
                -122.1510756, 
                12.0
            ], 
            "time": 1468478783.0
        }, 
        {
            "pos": [
                37.40583678, 
                -122.15107569, 
                12.0
            ], 
            "time": 1468478784.0
        }, 
        {
            "pos": [
                37.40583683, 
                -122.15107589, 
                12.0
            ], 
            "time": 1468478785.0
        }, 
        {
            "pos": [
                37.40583691, 
                -122.15107605, 
                12.0
            ], 
            "time": 1468478786.0
        }, 
        {
            "pos": [
                37.405837, 
                -122.15107621, 
                12.0
            ], 
            "time": 1468478787.0
        }, 
        {
            "pos": [
                37.4058372, 
                -122.15107628, 
                12.0
            ], 
            "time": 1468478788.0
        }, 
        {
            "pos": [
                37.40583724, 
                -122.15107638, 
                12.0
            ], 
            "time": 1468478789.0
        }, 
        {
            "pos": [
                37.40583724, 
                -122.1510765, 
                12.0
            ], 
            "time": 1468478790.0
        }, 
        {
            "pos": [
                37.40583729, 
                -122.15107661, 
                12.0
            ], 
            "time": 1468478791.0
        }, 
        {
            "pos": [
                37.40583737, 
                -122.15107664, 
                12.0
            ], 
            "time": 1468478792.0
        }, 
        {
            "pos": [
                37.40583719, 
                -122.15107675, 
                12.0
            ], 
            "time": 1468478793.0
        }, 
        {
            "pos": [
                37.40583708, 
                -122.15107688, 
                12.0
            ], 
            "time": 1468478794.0
        }, 
        {
            "pos": [
                37.40583704, 
                -122.15107696, 
                12.0
            ], 
            "time": 1468478795.0
        }, 
        {
            "pos": [
                37.40583697, 
                -122.15107709, 
                12.0
            ], 
            "time": 1468478796.0
        }, 
        {
            "pos": [
                37.4058368, 
                -122.15107722, 
                12.0
            ], 
            "time": 1468478797.0
        }, 
        {
            "pos": [
                37.40583679, 
                -122.15107743, 
                12.0
            ], 
            "time": 1468478798.0
        }, 
        {
            "pos": [
                37.40583678, 
                -122.15107738, 
                12.0
            ], 
            "time": 1468478799.0
        }, 
        {
            "pos": [
                37.40583671, 
                -122.15107745, 
                12.0
            ], 
            "time": 1468478800.0
        }, 
        {
            "pos": [
                37.40583668, 
                -122.1510775, 
                12.0
            ], 
            "time": 1468478801.0
        }, 
        {
            "pos": [
                37.40583657, 
                -122.15107751, 
                12.0
            ], 
            "time": 1468478802.0
        }, 
        {
            "pos": [
                37.40583646, 
                -122.15107754, 
                12.0
            ], 
            "time": 1468478803.0
        }, 
        {
            "pos": [
                37.40583634, 
                -122.15107765, 
                12.0
            ], 
            "time": 1468478804.0
        }, 
        {
            "pos": [
                37.40583622, 
                -122.15107776, 
                12.0
            ], 
            "time": 1468478805.0
        }, 
        {
            "pos": [
                37.40583611, 
                -122.15107782, 
                12.0
            ], 
            "time": 1468478806.0
        }, 
        {
            "pos": [
                37.40583612, 
                -122.15107781, 
                12.0
            ], 
            "time": 1468478807.0
        }, 
        {
            "pos": [
                37.40583623, 
                -122.15107786, 
                12.0
            ], 
            "time": 1468478808.0
        }, 
        {
            "pos": [
                37.40583634, 
                -122.15107803, 
                12.0
            ], 
            "time": 1468478809.0
        }, 
        {
            "pos": [
                37.40583638, 
                -122.15107813, 
                12.0
            ], 
            "time": 1468478810.0
        }, 
        {
            "pos": [
                37.40583663, 
                -122.15107813, 
                12.0
            ], 
            "time": 1468478811.0
        }, 
        {
            "pos": [
                37.40583674, 
                -122.15107821, 
                12.0
            ], 
            "time": 1468478812.0
        }, 
        {
            "pos": [
                37.40583677, 
                -122.15107821, 
                12.0
            ], 
            "time": 1468478813.0
        }, 
        {
            "pos": [
                37.4058373, 
                -122.15107856, 
                12.0
            ], 
            "time": 1468478814.0
        }, 
        {
            "pos": [
                37.40583758, 
                -122.15107879, 
                12.0
            ], 
            "time": 1468478815.0
        }, 
        {
            "pos": [
                37.40583764, 
                -122.15107884, 
                12.0
            ], 
            "time": 1468478816.0
        }, 
        {
            "pos": [
                37.40583766, 
                -122.15107896, 
                12.0
            ], 
            "time": 1468478817.0
        }, 
        {
            "pos": [
                37.40583773, 
                -122.15107902, 
                12.0
            ], 
            "time": 1468478818.0
        }, 
        {
            "pos": [
                37.40583802, 
                -122.15107918, 
                12.0
            ], 
            "time": 1468478819.0
        }, 
        {
            "pos": [
                37.40583821, 
                -122.15107936, 
                12.0
            ], 
            "time": 1468478820.0
        }, 
        {
            "pos": [
                37.40583825, 
                -122.15107943, 
                12.0
            ], 
            "time": 1468478821.0
        }, 
        {
            "pos": [
                37.40583868, 
                -122.15107968, 
                12.0
            ], 
            "time": 1468478822.0
        }, 
        {
            "pos": [
                37.40583911, 
                -122.15108004, 
                12.0
            ], 
            "time": 1468478823.0
        }, 
        {
            "pos": [
                37.40583948, 
                -122.15108014, 
                12.0
            ], 
            "time": 1468478824.0
        }, 
        {
            "pos": [
                37.40583954, 
                -122.15108051, 
                12.0
            ], 
            "time": 1468478825.0
        }, 
        {
            "pos": [
                37.40584003, 
                -122.15108075, 
                12.0
            ], 
            "time": 1468478826.0
        }, 
        {
            "pos": [
                37.40584054, 
                -122.151081, 
                12.0
            ], 
            "time": 1468478827.0
        }, 
        {
            "pos": [
                37.40584087, 
                -122.15108121, 
                12.0
            ], 
            "time": 1468478828.0
        }, 
        {
            "pos": [
                37.40584104, 
                -122.15108136, 
                12.0
            ], 
            "time": 1468478829.0
        }, 
        {
            "pos": [
                37.40584147, 
                -122.15108158, 
                12.0
            ], 
            "time": 1468478830.0
        }, 
        {
            "pos": [
                37.40584168, 
                -122.15108169, 
                12.0
            ], 
            "time": 1468478831.0
        }, 
        {
            "pos": [
                37.4058417, 
                -122.15108174, 
                12.0
            ], 
            "time": 1468478832.0
        }, 
        {
            "pos": [
                37.40584169, 
                -122.15108181, 
                12.0
            ], 
            "time": 1468478833.0
        }, 
        {
            "pos": [
                37.40584175, 
                -122.15108208, 
                12.0
            ], 
            "time": 1468478834.0
        }, 
        {
            "pos": [
                37.40584166, 
                -122.15108211, 
                12.0
            ], 
            "time": 1468478835.0
        }, 
        {
            "pos": [
                37.40584182, 
                -122.1510821, 
                12.0
            ], 
            "time": 1468478836.0
        }, 
        {
            "pos": [
                37.40584195, 
                -122.15108209, 
                12.0
            ], 
            "time": 1468478837.0
        }, 
        {
            "pos": [
                37.40584196, 
                -122.15108211, 
                12.0
            ], 
            "time": 1468478838.0
        }, 
        {
            "pos": [
                37.40584205, 
                -122.15108209, 
                12.0
            ], 
            "time": 1468478839.0
        }, 
        {
            "pos": [
                37.40584215, 
                -122.15108204, 
                12.0
            ], 
            "time": 1468478840.0
        }, 
        {
            "pos": [
                37.40584239, 
                -122.15108214, 
                12.0
            ], 
            "time": 1468478841.0
        }, 
        {
            "pos": [
                37.40584244, 
                -122.15108218, 
                12.0
            ], 
            "time": 1468478842.0
        }, 
        {
            "pos": [
                37.40584239, 
                -122.15108226, 
                12.0
            ], 
            "time": 1468478843.0
        }, 
        {
            "pos": [
                37.4058424, 
                -122.15108223, 
                12.0
            ], 
            "time": 1468478844.0
        }, 
        {
            "pos": [
                37.40584245, 
                -122.15108223, 
                12.0
            ], 
            "time": 1468478845.0
        }, 
        {
            "pos": [
                37.40584238, 
                -122.15108224, 
                12.0
            ], 
            "time": 1468478846.0
        }, 
        {
            "pos": [
                37.40584212, 
                -122.15108226, 
                12.0
            ], 
            "time": 1468478847.0
        }, 
        {
            "pos": [
                37.40584184, 
                -122.15108237, 
                12.0
            ], 
            "time": 1468478848.0
        }, 
        {
            "pos": [
                37.40584178, 
                -122.15108241, 
                12.0
            ], 
            "time": 1468478849.0
        }, 
        {
            "pos": [
                37.40584176, 
                -122.15108243, 
                12.0
            ], 
            "time": 1468478850.0
        }, 
        {
            "pos": [
                37.40584173, 
                -122.15108242, 
                12.0
            ], 
            "time": 1468478851.0
        }, 
        {
            "pos": [
                37.40584165, 
                -122.15108243, 
                12.0
            ], 
            "time": 1468478852.0
        }, 
        {
            "pos": [
                37.40584162, 
                -122.15108242, 
                12.0
            ], 
            "time": 1468478853.0
        }, 
        {
            "pos": [
                37.40584159, 
                -122.15108251, 
                12.0
            ], 
            "time": 1468478854.0
        }, 
        {
            "pos": [
                37.40584145, 
                -122.15108258, 
                12.0
            ], 
            "time": 1468478855.0
        }, 
        {
            "pos": [
                37.40584137, 
                -122.15108261, 
                12.0
            ], 
            "time": 1468478856.0
        }, 
        {
            "pos": [
                37.40584135, 
                -122.1510826, 
                12.0
            ], 
            "time": 1468478857.0
        }, 
        {
            "pos": [
                37.40584132, 
                -122.15108264, 
                12.0
            ], 
            "time": 1468478858.0
        }, 
        {
            "pos": [
                37.40584123, 
                -122.15108266, 
                12.0
            ], 
            "time": 1468478859.0
        }, 
        {
            "pos": [
                37.40584121, 
                -122.15108265, 
                12.0
            ], 
            "time": 1468478860.0
        }, 
        {
            "pos": [
                37.40584114, 
                -122.15108267, 
                12.0
            ], 
            "time": 1468478861.0
        }, 
        {
            "pos": [
                37.40584105, 
                -122.15108272, 
                12.0
            ], 
            "time": 1468478862.0
        }, 
        {
            "pos": [
                37.40584097, 
                -122.15108271, 
                12.0
            ], 
            "time": 1468478863.0
        }, 
        {
            "pos": [
                37.40584096, 
                -122.15108272, 
                12.0
            ], 
            "time": 1468478864.0
        }, 
        {
            "pos": [
                37.40584094, 
                -122.15108269, 
                12.0
            ], 
            "time": 1468478865.0
        }, 
        {
            "pos": [
                37.40584101, 
                -122.15108266, 
                12.0
            ], 
            "time": 1468478866.0
        }, 
        {
            "pos": [
                37.40584108, 
                -122.15108262, 
                12.0
            ], 
            "time": 1468478867.0
        }, 
        {
            "pos": [
                37.40584115, 
                -122.15108255, 
                12.0
            ], 
            "time": 1468478868.0
        }, 
        {
            "pos": [
                37.40584125, 
                -122.15108251, 
                12.0
            ], 
            "time": 1468478869.0
        }, 
        {
            "pos": [
                37.40584131, 
                -122.15108257, 
                12.0
            ], 
            "time": 1468478870.0
        }, 
        {
            "pos": [
                37.40584142, 
                -122.15108251, 
                12.0
            ], 
            "time": 1468478871.0
        }, 
        {
            "pos": [
                37.40584153, 
                -122.15108246, 
                12.0
            ], 
            "time": 1468478872.0
        }, 
        {
            "pos": [
                37.40584157, 
                -122.15108245, 
                12.0
            ], 
            "time": 1468478873.0
        }, 
        {
            "pos": [
                37.40584194, 
                -122.15108265, 
                12.0
            ], 
            "time": 1468478874.0
        }, 
        {
            "pos": [
                37.40584243, 
                -122.15108295, 
                12.0
            ], 
            "time": 1468478875.0
        }, 
        {
            "pos": [
                37.40584257, 
                -122.15108296, 
                12.0
            ], 
            "time": 1468478876.0
        }, 
        {
            "pos": [
                37.40584298, 
                -122.15108327, 
                12.0
            ], 
            "time": 1468478877.0
        }, 
        {
            "pos": [
                37.405843, 
                -122.15108322, 
                12.0
            ], 
            "time": 1468478878.0
        }, 
        {
            "pos": [
                37.40584331, 
                -122.15108336, 
                12.0
            ], 
            "time": 1468478879.0
        }, 
        {
            "pos": [
                37.40584366, 
                -122.15108355, 
                12.0
            ], 
            "time": 1468478880.0
        }, 
        {
            "pos": [
                37.40584359, 
                -122.15108357, 
                12.0
            ], 
            "time": 1468478881.0
        }, 
        {
            "pos": [
                37.40584369, 
                -122.1510835, 
                12.0
            ], 
            "time": 1468478882.0
        }, 
        {
            "pos": [
                37.4058437, 
                -122.15108344, 
                12.0
            ], 
            "time": 1468478883.0
        }, 
        {
            "pos": [
                37.40584365, 
                -122.15108345, 
                12.0
            ], 
            "time": 1468478884.0
        }, 
        {
            "pos": [
                37.40584363, 
                -122.15108348, 
                12.0
            ], 
            "time": 1468478885.0
        }, 
        {
            "pos": [
                37.40584354, 
                -122.1510835, 
                12.0
            ], 
            "time": 1468478886.0
        }, 
        {
            "pos": [
                37.40584352, 
                -122.15108346, 
                12.0
            ], 
            "time": 1468478887.0
        }, 
        {
            "pos": [
                37.40584345, 
                -122.15108349, 
                12.0
            ], 
            "time": 1468478888.0
        }, 
        {
            "pos": [
                37.40584347, 
                -122.15108349, 
                12.0
            ], 
            "time": 1468478889.0
        }, 
        {
            "pos": [
                37.40584335, 
                -122.15108351, 
                12.0
            ], 
            "time": 1468478890.0
        }, 
        {
            "pos": [
                37.40584336, 
                -122.15108353, 
                12.0
            ], 
            "time": 1468478891.0
        }, 
        {
            "pos": [
                37.40584334, 
                -122.15108355, 
                12.0
            ], 
            "time": 1468478892.0
        }, 
        {
            "pos": [
                37.40584336, 
                -122.15108357, 
                12.0
            ], 
            "time": 1468478893.0
        }, 
        {
            "pos": [
                37.40584344, 
                -122.15108359, 
                12.0
            ], 
            "time": 1468478894.0
        }, 
        {
            "pos": [
                37.40584341, 
                -122.15108367, 
                12.0
            ], 
            "time": 1468478895.0
        }, 
        {
            "pos": [
                37.40584351, 
                -122.15108373, 
                12.0
            ], 
            "time": 1468478896.0
        }, 
        {
            "pos": [
                37.40584338, 
                -122.15108384, 
                12.0
            ], 
            "time": 1468478897.0
        }, 
        {
            "pos": [
                37.40584345, 
                -122.15108391, 
                12.0
            ], 
            "time": 1468478898.0
        }, 
        {
            "pos": [
                37.40584344, 
                -122.15108397, 
                12.0
            ], 
            "time": 1468478899.0
        }, 
        {
            "pos": [
                37.40584332, 
                -122.1510841, 
                12.0
            ], 
            "time": 1468478900.0
        }, 
        {
            "pos": [
                37.40584337, 
                -122.15108409, 
                12.0
            ], 
            "time": 1468478901.0
        }, 
        {
            "pos": [
                37.40584344, 
                -122.15108414, 
                12.0
            ], 
            "time": 1468478902.0
        }, 
        {
            "pos": [
                37.40584348, 
                -122.15108421, 
                12.0
            ], 
            "time": 1468478903.0
        }, 
        {
            "pos": [
                37.40584341, 
                -122.1510843, 
                12.0
            ], 
            "time": 1468478904.0
        }, 
        {
            "pos": [
                37.4058434, 
                -122.1510844, 
                12.0
            ], 
            "time": 1468478905.0
        }, 
        {
            "pos": [
                37.40584321, 
                -122.1510845, 
                12.0
            ], 
            "time": 1468478906.0
        }, 
        {
            "pos": [
                37.40584312, 
                -122.15108462, 
                12.0
            ], 
            "time": 1468478907.0
        }, 
        {
            "pos": [
                37.40584306, 
                -122.15108471, 
                12.0
            ], 
            "time": 1468478908.0
        }, 
        {
            "pos": [
                37.40584306, 
                -122.15108477, 
                12.0
            ], 
            "time": 1468478909.0
        }, 
        {
            "pos": [
                37.405843, 
                -122.15108489, 
                12.0
            ], 
            "time": 1468478910.0
        }, 
        {
            "pos": [
                37.40584294, 
                -122.15108493, 
                12.0
            ], 
            "time": 1468478911.0
        }, 
        {
            "pos": [
                37.40584281, 
                -122.15108508, 
                12.0
            ], 
            "time": 1468478912.0
        }, 
        {
            "pos": [
                37.40584266, 
                -122.15108518, 
                12.0
            ], 
            "time": 1468478913.0
        }, 
        {
            "pos": [
                37.40584263, 
                -122.15108526, 
                12.0
            ], 
            "time": 1468478914.0
        }, 
        {
            "pos": [
                37.40584253, 
                -122.15108533, 
                12.0
            ], 
            "time": 1468478915.0
        }, 
        {
            "pos": [
                37.40584241, 
                -122.15108545, 
                12.0
            ], 
            "time": 1468478916.0
        }, 
        {
            "pos": [
                37.40584238, 
                -122.15108553, 
                12.0
            ], 
            "time": 1468478917.0
        }, 
        {
            "pos": [
                37.40584241, 
                -122.15108561, 
                12.0
            ], 
            "time": 1468478918.0
        }, 
        {
            "pos": [
                37.40584241, 
                -122.1510857, 
                12.0
            ], 
            "time": 1468478919.0
        }, 
        {
            "pos": [
                37.40584243, 
                -122.15108577, 
                12.0
            ], 
            "time": 1468478920.0
        }, 
        {
            "pos": [
                37.40584231, 
                -122.15108591, 
                12.0
            ], 
            "time": 1468478921.0
        }, 
        {
            "pos": [
                37.40584214, 
                -122.15108599, 
                12.0
            ], 
            "time": 1468478922.0
        }, 
        {
            "pos": [
                37.40584206, 
                -122.15108605, 
                12.0
            ], 
            "time": 1468478923.0
        }, 
        {
            "pos": [
                37.40584207, 
                -122.15108608, 
                12.0
            ], 
            "time": 1468478924.0
        }, 
        {
            "pos": [
                37.40584197, 
                -122.15108617, 
                12.0
            ], 
            "time": 1468478925.0
        }, 
        {
            "pos": [
                37.40584185, 
                -122.15108626, 
                12.0
            ], 
            "time": 1468478926.0
        }, 
        {
            "pos": [
                37.40584179, 
                -122.1510863, 
                12.0
            ], 
            "time": 1468478927.0
        }, 
        {
            "pos": [
                37.40584163, 
                -122.15108641, 
                12.0
            ], 
            "time": 1468478928.0
        }, 
        {
            "pos": [
                37.40584165, 
                -122.15108642, 
                12.0
            ], 
            "time": 1468478929.0
        }, 
        {
            "pos": [
                37.40584147, 
                -122.1510865, 
                12.0
            ], 
            "time": 1468478930.0
        }, 
        {
            "pos": [
                37.40584144, 
                -122.15108653, 
                12.0
            ], 
            "time": 1468478931.0
        }, 
        {
            "pos": [
                37.40584139, 
                -122.15108659, 
                12.0
            ], 
            "time": 1468478932.0
        }, 
        {
            "pos": [
                37.40584129, 
                -122.15108667, 
                12.0
            ], 
            "time": 1468478933.0
        }, 
        {
            "pos": [
                37.40584122, 
                -122.1510867, 
                12.0
            ], 
            "time": 1468478934.0
        }, 
        {
            "pos": [
                37.40584119, 
                -122.1510868, 
                12.0
            ], 
            "time": 1468478935.0
        }, 
        {
            "pos": [
                37.40584107, 
                -122.15108694, 
                12.0
            ], 
            "time": 1468478936.0
        }, 
        {
            "pos": [
                37.40584103, 
                -122.15108701, 
                12.0
            ], 
            "time": 1468478937.0
        }, 
        {
            "pos": [
                37.40584095, 
                -122.15108712, 
                12.0
            ], 
            "time": 1468478938.0
        }, 
        {
            "pos": [
                37.40584096, 
                -122.15108714, 
                12.0
            ], 
            "time": 1468478939.0
        }, 
        {
            "pos": [
                37.40584088, 
                -122.15108721, 
                12.0
            ], 
            "time": 1468478940.0
        }, 
        {
            "pos": [
                37.40584083, 
                -122.15108725, 
                12.0
            ], 
            "time": 1468478941.0
        }, 
        {
            "pos": [
                37.40584084, 
                -122.15108726, 
                12.0
            ], 
            "time": 1468478942.0
        }, 
        {
            "pos": [
                37.40584074, 
                -122.15108732, 
                12.0
            ], 
            "time": 1468478943.0
        }, 
        {
            "pos": [
                37.40584073, 
                -122.15108729, 
                12.0
            ], 
            "time": 1468478944.0
        }, 
        {
            "pos": [
                37.40584064, 
                -122.15108734, 
                12.0
            ], 
            "time": 1468478945.0
        }, 
        {
            "pos": [
                37.40584055, 
                -122.15108741, 
                12.0
            ], 
            "time": 1468478946.0
        }, 
        {
            "pos": [
                37.40584049, 
                -122.15108746, 
                12.0
            ], 
            "time": 1468478947.0
        }, 
        {
            "pos": [
                37.40584048, 
                -122.15108747, 
                12.0
            ], 
            "time": 1468478948.0
        }, 
        {
            "pos": [
                37.40584044, 
                -122.15108749, 
                12.0
            ], 
            "time": 1468478949.0
        }, 
        {
            "pos": [
                37.40584034, 
                -122.1510876, 
                12.0
            ], 
            "time": 1468478950.0
        }, 
        {
            "pos": [
                37.40584032, 
                -122.15108766, 
                12.0
            ], 
            "time": 1468478951.0
        }, 
        {
            "pos": [
                37.40584025, 
                -122.15108773, 
                12.0
            ], 
            "time": 1468478952.0
        }, 
        {
            "pos": [
                37.40577811, 
                -122.15115487, 
                -1.0
            ], 
            "time": 1468478953.0
        }, 
        {
            "pos": [
                37.40577393, 
                -122.15115827, 
                -1.0
            ], 
            "time": 1468478954.0
        }, 
        {
            "pos": [
                37.40577496, 
                -122.15116838, 
                2.0
            ], 
            "time": 1468478955.0
        }, 
        {
            "pos": [
                37.40577242, 
                -122.15117284, 
                3.0
            ], 
            "time": 1468478956.0
        }, 
        {
            "pos": [
                37.40577065, 
                -122.15117882, 
                4.0
            ], 
            "time": 1468478957.0
        }, 
        {
            "pos": [
                37.40577013, 
                -122.15118333, 
                4.0
            ], 
            "time": 1468478958.0
        }, 
        {
            "pos": [
                37.40577673, 
                -122.15118336, 
                5.0
            ], 
            "time": 1468478959.0
        }, 
        {
            "pos": [
                37.40578198, 
                -122.15118856, 
                6.0
            ], 
            "time": 1468478960.0
        }, 
        {
            "pos": [
                37.40578515, 
                -122.1511856, 
                5.0
            ], 
            "time": 1468478961.0
        }, 
        {
            "pos": [
                37.40578356, 
                -122.15118682, 
                5.0
            ], 
            "time": 1468478962.0
        }, 
        {
            "pos": [
                37.4057848, 
                -122.15118621, 
                5.0
            ], 
            "time": 1468478963.0
        }, 
        {
            "pos": [
                37.40578485, 
                -122.15118496, 
                5.0
            ], 
            "time": 1468478964.0
        }, 
        {
            "pos": [
                37.40578629, 
                -122.15118443, 
                5.0
            ], 
            "time": 1468478965.0
        }, 
        {
            "pos": [
                37.40578647, 
                -122.15118423, 
                5.0
            ], 
            "time": 1468478966.0
        }, 
        {
            "pos": [
                37.40578669, 
                -122.15118418, 
                5.0
            ], 
            "time": 1468478967.0
        }, 
        {
            "pos": [
                37.40578671, 
                -122.15118414, 
                5.0
            ], 
            "time": 1468478968.0
        }, 
        {
            "pos": [
                37.40578676, 
                -122.15118413, 
                5.0
            ], 
            "time": 1468478969.0
        }, 
        {
            "pos": [
                37.40578681, 
                -122.15118411, 
                5.0
            ], 
            "time": 1468478970.0
        }, 
        {
            "pos": [
                37.40578682, 
                -122.1511841, 
                5.0
            ], 
            "time": 1468478971.0
        }, 
        {
            "pos": [
                37.40578688, 
                -122.15118407, 
                5.0
            ], 
            "time": 1468478972.0
        }, 
        {
            "pos": [
                37.40578695, 
                -122.15118406, 
                5.0
            ], 
            "time": 1468478973.0
        }, 
        {
            "pos": [
                37.405787, 
                -122.15118402, 
                5.0
            ], 
            "time": 1468478974.0
        }, 
        {
            "pos": [
                37.40578707, 
                -122.15118395, 
                5.0
            ], 
            "time": 1468478975.0
        }, 
        {
            "pos": [
                37.40578714, 
                -122.1511839, 
                5.0
            ], 
            "time": 1468478976.0
        }
    ]
}